sqlalchemy_yugabytedb/__init__.py
sqlalchemy_yugabytedb/base.py
sqlalchemy_yugabytedb/psycopg2.py
sqlalchemy_yugabytedb/requirements.py
sqlalchemy_yugabytedb-1.0.0.1.dist-info/METADATA
sqlalchemy_yugabytedb-1.0.0.1.dist-info/WHEEL
sqlalchemy_yugabytedb-1.0.0.1.dist-info/entry_points.txt
sqlalchemy_yugabytedb-1.0.0.1.dist-info/top_level.txt
sqlalchemy_yugabytedb-1.0.0.1.dist-info/RECORD
