Metadata-Version: 2.1
Name: sqlalchemy-yugabytedb
Version: 1.0.0.1
Summary: YugabyteDB dialect for SQLAlchemy
Home-page: https://github.com/yugabyte/sqlalchemy-yugabytedb
Author: Yugabyte
Author-email: 
License: http://www.apache.org/licenses/LICENSE-2.0
Project-URL: Documentation, https://docs.yugabyte.com/
Project-URL: Source, https://github.com/yugabyte/sqlalchemy-yugabytedb
Keywords: SQLAlchemy YugabyteDB
Platform: UNKNOWN
Classifier: License :: OSI Approved :: Apache Software License
Classifier: Programming Language :: Python :: 3
Classifier: Programming Language :: Python :: 3 :: Only
Classifier: Programming Language :: Python :: 3.6
Classifier: Programming Language :: Python :: 3.7
Classifier: Programming Language :: Python :: 3.8
Classifier: Programming Language :: Python :: 3.9
Requires-Dist: SQLAlchemy
Requires-Dist: psycopg2-yugabytedb
